{
  "heroes": [
    {
      "id": 1,
      "name": "Первой герой",
      "description": "Первой герой со стихией огня",
      "element": "fire"
    },
    {
      "id": 2,
      "name": "Второй герой ",
      "description": "Второй герой со стихией воды",
      "element": "water"
    },
    {
      "id": 3,
      "name": "Третий герой",
      "description": "Третий герой со стихией ветра",
      "element": "wind"
    },
    {
      "id": 4,
      "name": "Четвертый герой",
      "description": "Четвертый герой со стихией земли",
      "element": "earth"
    },
    {
      "id": 5,
      "name": "Пятый герой",
      "description": "Пятый герой со стихией огня ",
      "element": "fire"
    }
  ],
  "filters": [
    {
      "id": "all",
      "element": "all",
      "name": "Все",
      "className": "btn btn-outline-dark"
    },
    {
      "id": "fire",
      "element": "fire",
      "name": "Огонь",
      "className": "btn btn-danger"
    },
    {
      "id": "water",
      "element": "water",
      "name": "Вода",
      "className": "btn btn-primary"
    },
    {
      "id": "wind",
      "element": "wind",
      "name": "Ветер",
      "className": "btn btn-success"
    },
    {
      "id": "earth",
      "element": "earth",
      "name": "Земля",
      "className": "btn btn-secondary"
    }
  ]
}